CHANGES
LICENSE
README.md
pyproject.toml
setup.cfg
setup.py
scripts/convert_unitame
scripts/ebookmaker
scripts/rhyme_compiler
src/ebookmaker/CommonCode.py
src/ebookmaker/EbookMaker.py
src/ebookmaker/HTMLChunker.py
src/ebookmaker/ParserFactory.py
src/ebookmaker/Spider.py
src/ebookmaker/Unitame.py
src/ebookmaker/UnitameData.py
src/ebookmaker/Version.py
src/ebookmaker/WriterFactory.py
src/ebookmaker/__init__.py
src/ebookmaker/utils.py
src/ebookmaker.egg-info/PKG-INFO
src/ebookmaker.egg-info/SOURCES.txt
src/ebookmaker.egg-info/dependency_links.txt
src/ebookmaker.egg-info/requires.txt
src/ebookmaker.egg-info/top_level.txt
src/ebookmaker/mydocutils/__init__.py
src/ebookmaker/mydocutils/nodes.py
src/ebookmaker/mydocutils/gutenberg/__init__.py
src/ebookmaker/mydocutils/gutenberg/parsers/__init__.py
src/ebookmaker/mydocutils/gutenberg/parsers/pg-footer.rst
src/ebookmaker/mydocutils/gutenberg/parsers/pg-header.rst
src/ebookmaker/mydocutils/gutenberg/transforms/__init__.py
src/ebookmaker/mydocutils/gutenberg/writers/__init__.py
src/ebookmaker/mydocutils/gutenberg/writers/nroff.py
src/ebookmaker/mydocutils/parsers/__init__.py
src/ebookmaker/mydocutils/parsers/default_style.rst
src/ebookmaker/mydocutils/transforms/__init__.py
src/ebookmaker/mydocutils/transforms/parts.py
src/ebookmaker/mydocutils/writers/__init__.py
src/ebookmaker/mydocutils/writers/epub2.py
src/ebookmaker/mydocutils/writers/nroff.py
src/ebookmaker/mydocutils/writers/rst2all.css
src/ebookmaker/mydocutils/writers/rst2epub.css
src/ebookmaker/mydocutils/writers/rst2html.css
src/ebookmaker/mydocutils/writers/xetex.py
src/ebookmaker/mydocutils/writers/xhtml1.py
src/ebookmaker/packagers/GzipPackager.py
src/ebookmaker/packagers/HTMLPackager.py
src/ebookmaker/packagers/PDFPackager.py
src/ebookmaker/packagers/PushPackager.py
src/ebookmaker/packagers/RSTPackager.py
src/ebookmaker/packagers/TxtPackager.py
src/ebookmaker/packagers/__init__.py
src/ebookmaker/parsers/AuxParser.py
src/ebookmaker/parsers/CSSParser.py
src/ebookmaker/parsers/GutenbergTextParser.py
src/ebookmaker/parsers/HTMLParser.py
src/ebookmaker/parsers/ImageParser.py
src/ebookmaker/parsers/RSTParser.py
src/ebookmaker/parsers/WrapperParser.py
