Metadata-Version: 2.1
Name: ebookmaker
Version: 0.13.8
Summary: The Project Gutenberg tool to generate EPUBs and other ebook formats.
Home-page: https://github.com/gutenbergtools/ebookmaker/
Author: Marcello Perathoner
Maintainer: Eric Hellman
Maintainer-email: eric@hellman.net
License: GPL v3
Keywords: ebook epub kindle pdf rst reST reStructuredText project gutenberg format conversion
Platform: OS-independent
Classifier: Topic :: Text Processing
Classifier: License :: OSI Approved :: GNU General Public License (GPL)
Classifier: Environment :: Console
Classifier: Operating System :: OS Independent
Classifier: Intended Audience :: Other Audience
Classifier: Programming Language :: Python
Classifier: Programming Language :: Python :: 3.9
Classifier: Programming Language :: Python :: 3.10
Classifier: Programming Language :: Python :: 3.11
License-File: LICENSE
Requires-Dist: pillow>=8.3.2
Requires-Dist: cssutils
Requires-Dist: docutils>=0.18.1
Requires-Dist: lxml
Requires-Dist: roman
Requires-Dist: requests
Requires-Dist: six>=1.4.1
Requires-Dist: libgutenberg[covers]>=0.10.22
Requires-Dist: cchardet==2.2.0a2
Requires-Dist: beautifulsoup4
Requires-Dist: html5lib
